PYMEcs/__init__.py
PYMEcs/pyme_warnings.py
PYMEcs/version.py
PYMEcs/Acquire/__init__.py
PYMEcs/Acquire/Actions/__init__.py
PYMEcs/Acquire/Actions/custom.py
PYMEcs/Acquire/Hardware/LPthreadedSimple.py
PYMEcs/Acquire/Hardware/LPthreadedSimpleSim.py
PYMEcs/Acquire/Hardware/NikonTiFlaskServer.py
PYMEcs/Acquire/Hardware/NikonTiFlaskServerT.py
PYMEcs/Acquire/Hardware/NikonTiRESTClient.py
PYMEcs/Acquire/Hardware/NikonTiSim.py
PYMEcs/Acquire/Hardware/__init__.py
PYMEcs/Acquire/Hardware/driftTrackGUI.py
PYMEcs/Acquire/Hardware/driftTrackGUI_n.py
PYMEcs/Acquire/Hardware/driftTracking.py
PYMEcs/Acquire/Hardware/driftTracking_n.py
PYMEcs/Acquire/Hardware/fakeCamX.py
PYMEcs/Acquire/Hardware/offsetPiezoRESTCorrelLog.py
PYMEcs/Acquire/Hardware/Piezos/joystick_c867_digital.py
PYMEcs/Analysis/MBMcollection.py
PYMEcs/Analysis/MINFLUX.py
PYMEcs/Analysis/MapUtils.py
PYMEcs/Analysis/NPC.py
PYMEcs/Analysis/Paraflux.py
PYMEcs/Analysis/Simpler.py
PYMEcs/Analysis/Sofi.py
PYMEcs/Analysis/__init__.py
PYMEcs/Analysis/decSofi.py
PYMEcs/Analysis/eventProperties.py
PYMEcs/Analysis/fitDarkTimes.py
PYMEcs/Analysis/objectVolumes.py
PYMEcs/Analysis/offlineTracker.py
PYMEcs/Analysis/stackTracker.py
PYMEcs/Analysis/timeSeries.py
PYMEcs/Analysis/trackFiducials.py
PYMEcs/Analysis/zerocross.py
PYMEcs/IO/MINFLUX.py
PYMEcs/IO/NPC.py
PYMEcs/IO/__init__.py
PYMEcs/IO/darkTimes.py
PYMEcs/IO/picasso.py
PYMEcs/IO/tabular.py
PYMEcs/experimental/CalcZfactor.py
PYMEcs/experimental/FRC.py
PYMEcs/experimental/ImageJROItools.py
PYMEcs/experimental/MINFLUX.py
PYMEcs/experimental/NPCcalcLM.py
PYMEcs/experimental/Simpler.py
PYMEcs/experimental/Sofi.py
PYMEcs/experimental/__init__.py
PYMEcs/experimental/binEventProperty.py
PYMEcs/experimental/chaining.py
PYMEcs/experimental/clusterTrack.py
PYMEcs/experimental/combine_maps.py
PYMEcs/experimental/eventProcessing.py
PYMEcs/experimental/fiducials.py
PYMEcs/experimental/fiducialsNew.py
PYMEcs/experimental/mapTools.py
PYMEcs/experimental/meas2DplotDh5view.py
pyme_extra-1.0.5.post0.dist-info/licenses/LICENSE
pyme_extra-1.0.5.post0.dist-info/METADATA
pyme_extra-1.0.5.post0.dist-info/WHEEL
pyme_extra-1.0.5.post0.dist-info/entry_points.txt
pyme_extra-1.0.5.post0.dist-info/top_level.txt
pyme_extra-1.0.5.post0.dist-info/RECORD
