Metadata-Version: 2.4
Name: PYME-extra
Version: 1.0.5.post0
Summary: Plugins and associated code for PYME
Author-email: Christian Soeller <christian.soeller@unibe.ch>
License-Expression: GPL-3.0-or-later
Project-URL: Repository, https://github.com/csoeller/PYME-extra
Classifier: Programming Language :: Python :: 3
Classifier: Operating System :: OS Independent
Requires-Python: >=3.10
License-File: LICENSE
Requires-Dist: python-microscopy
Requires-Dist: statsmodels
Requires-Dist: roifile
Requires-Dist: colorcet
Requires-Dist: zarr<3,>=2
Requires-Dist: seaborn
Requires-Dist: mrcfile
Requires-Dist: circle-fit
Requires-Dist: alphashape
Requires-Dist: pywin32; platform_system == "Windows"
Provides-Extra: opt
Requires-Dist: openpyxl; extra == "opt"
Requires-Dist: tabulate; extra == "opt"
Dynamic: license-file
